dns_observe/__init__.py
dns_observe/__main__.py
dns_observe/dns.py
dns_observe-0.6.5.dist-info/LICENSE.txt
dns_observe-0.6.5.dist-info/METADATA
dns_observe-0.6.5.dist-info/WHEEL
dns_observe-0.6.5.dist-info/entry_points.txt
dns_observe-0.6.5.dist-info/top_level.txt
dns_observe-0.6.5.dist-info/RECORD
