Metadata-Version: 2.1
Name: dns-observe
Version: 0.6.5
Summary: a simple client to observe dns pollution network situation under Great Firewall.
Author-email: xavier skip <xavierskip@gmail.com>
Project-URL: Homepage, https://github.com/xavierskip/dns-observe
Project-URL: Bug Tracker, https://github.com/xavierskip/dns-observe/issues
Classifier: Programming Language :: Python :: 3
Classifier: License :: OSI Approved :: MIT License
Classifier: Operating System :: OS Independent
Requires-Python: >=3.7
License-File: LICENSE.txt
